neurolink/__init__.py
neurolink/help.py
neurolink/neurolink.py
neurolink/Scripts/__init__.py
neurolink/Scripts/__keras__.py
neurolink/Scripts/__pytorch__.py
neurolink/Scripts/__tflearn__.py
neurolink/include/__init__.py
neurolink/include/__load__.py
neurolink/include/__process__.py
neurolink/lib/__init__.py
neurolink-0.0.0.dist-info/LICENSE.txt
neurolink-0.0.0.dist-info/METADATA
neurolink-0.0.0.dist-info/WHEEL
neurolink-0.0.0.dist-info/top_level.txt
neurolink-0.0.0.dist-info/RECORD
