Metadata-Version: 2.1
Name: neurolink
Version: 0.0.0
Summary: NeuroLink is a Python package in active development that aims to provide various AI capabilities, including a chatbot, image processing, audio processing, Django & Flask support, and more.
Home-page: https://github.com/muhammad-fiaz/neurolink
Author: Muhammad Fiaz
Author-email: 
License: Apache Software License (Apache 2.0)
Project-URL: Source Code, https://github.com/muhammad-fiaz/neurolink
Project-URL: Bug Tracker, https://github.com/muhammad-fiaz/neurolink/issues
Project-URL: Documentation, https://github.com/muhammad-fiaz
Keywords: neural networks,neurolink,machine learning,artificial intelligence,ai,ml,chatbot,image processing,audio processing,django,flask
Classifier: Development Status :: 1 - Planning
Classifier: Intended Audience :: Developers
Classifier: Programming Language :: Python :: 3
Classifier: License :: OSI Approved :: Apache Software License
Classifier: Operating System :: Unix
Classifier: Operating System :: MacOS :: MacOS X
Classifier: Operating System :: Microsoft :: Windows
Requires-Python: >=3.8
License-File: LICENSE.txt
Requires-Dist: pip (==23.1.2)
Requires-Dist: attrs
Requires-Dist: argparse
Requires-Dist: wheel
Requires-Dist: packages
Requires-Dist: google
Requires-Dist: cryptography
Requires-Dist: Pillow
Requires-Dist: docutils
Requires-Dist: Jinja2
Requires-Dist: keyring
Requires-Dist: setuptools
Requires-Dist: packaging
Requires-Dist: pyparsing
Requires-Dist: zipp
Requires-Dist: nltk
Requires-Dist: numpy
Requires-Dist: tensorflow
Requires-Dist: tflearn
Requires-Dist: torch
